ai_benchmark/__init__.py
ai_benchmark/config.py
ai_benchmark/console.py
ai_benchmark/core.py
ai_benchmark/model_utils.py
ai_benchmark/models.py
ai_benchmark/update_utils.py
ai_benchmark/utils.py
ai_benchmark/data/classification/0.jpg
ai_benchmark/data/classification/1.jpg
ai_benchmark/data/classification/10.jpg
ai_benchmark/data/classification/11.jpg
ai_benchmark/data/classification/12.jpg
ai_benchmark/data/classification/13.jpg
ai_benchmark/data/classification/14.jpg
ai_benchmark/data/classification/15.jpg
ai_benchmark/data/classification/16.jpg
ai_benchmark/data/classification/17.jpg
ai_benchmark/data/classification/18.jpg
ai_benchmark/data/classification/19.jpg
ai_benchmark/data/classification/2.jpg
ai_benchmark/data/classification/20.jpg
ai_benchmark/data/classification/21.jpg
ai_benchmark/data/classification/22.jpg
ai_benchmark/data/classification/23.jpg
ai_benchmark/data/classification/24.jpg
ai_benchmark/data/classification/25.jpg
ai_benchmark/data/classification/26.jpg
ai_benchmark/data/classification/27.jpg
ai_benchmark/data/classification/28.jpg
ai_benchmark/data/classification/29.jpg
ai_benchmark/data/classification/3.jpg
ai_benchmark/data/classification/30.jpg
ai_benchmark/data/classification/31.jpg
ai_benchmark/data/classification/32.jpg
ai_benchmark/data/classification/33.jpg
ai_benchmark/data/classification/34.jpg
ai_benchmark/data/classification/35.jpg
ai_benchmark/data/classification/36.jpg
ai_benchmark/data/classification/37.jpg
ai_benchmark/data/classification/38.jpg
ai_benchmark/data/classification/39.jpg
ai_benchmark/data/classification/4.jpg
ai_benchmark/data/classification/40.jpg
ai_benchmark/data/classification/41.jpg
ai_benchmark/data/classification/42.jpg
ai_benchmark/data/classification/43.jpg
ai_benchmark/data/classification/44.jpg
ai_benchmark/data/classification/45.jpg
ai_benchmark/data/classification/46.jpg
ai_benchmark/data/classification/47.jpg
ai_benchmark/data/classification/48.jpg
ai_benchmark/data/classification/49.jpg
new_ai_benchmark-2.7.0.dist-info/METADATA
new_ai_benchmark-2.7.0.dist-info/WHEEL
new_ai_benchmark-2.7.0.dist-info/top_level.txt
new_ai_benchmark-2.7.0.dist-info/RECORD
