Metadata-Version: 2.1
Name: new-ai-benchmark
Version: 2.7.0
Summary: AI Benchmark is an open source python library for evaluating AI performance of various hardware platforms, including CPUs, GPUs and TPUs.
Author-email: Andrey Ignatov <andrey@vision.ee.ethz.ch>
Maintainer-email: Johnny Núñez <jnunezca11@alumnes.ub.edu>
License: MIT License
Keywords: AI,Benchmark,Tensorflow,Machine Learning,Inference,Training
Classifier: Intended Audience :: Developers
Classifier: Intended Audience :: Education
Classifier: Intended Audience :: Science/Research
Classifier: Intended Audience :: Information Technology
Classifier: Programming Language :: Python :: 3.8
Classifier: Programming Language :: Python :: 3.9
Classifier: Programming Language :: Python :: 3.10
Classifier: Programming Language :: Python :: 3.11
Classifier: Programming Language :: Python :: 3.12
Classifier: Operating System :: OS Independent
Classifier: Topic :: Scientific/Engineering
Classifier: Topic :: Scientific/Engineering :: Artificial Intelligence
Classifier: Topic :: Software Development :: Testing
Classifier: Topic :: System :: Benchmark
Requires-Dist: numpy
Requires-Dist: psutil
Requires-Dist: py-cpuinfo
Requires-Dist: pillow
Requires-Dist: setuptools
Requires-Dist: requests
Requires-Dist: pypandoc
